apispec_drf/__init__.py
apispec_drf/builder.py
apispec_drf/decorators.py
apispec_drf/urls.py
apispec_drf/version.py
apispec_drf/management/__init__.py
apispec_drf/management/commands/__init__.py
apispec_drf/management/commands/generate_swagger_spec.py
apispec_drf/static/swagger-ui/oauth2_redirect.html
apispec_drf/static/swagger-ui/swagger-ui-bundle.js
apispec_drf/static/swagger-ui/swagger-ui-standalone-preset.js
apispec_drf/static/swagger-ui/swagger-ui.css
apispec_drf/templates/apispec_drf/swagger-ui.html
apispec_djangorestframework-1.1.1.dist-info/METADATA
apispec_djangorestframework-1.1.1.dist-info/WHEEL
apispec_djangorestframework-1.1.1.dist-info/top_level.txt
apispec_djangorestframework-1.1.1.dist-info/RECORD
