Metadata-Version: 2.1
Name: apispec-djangorestframework
Version: 1.1.1
Summary: DjangoRestFramework 3.6.x APISpec generator
Home-page: UNKNOWN
Author: Concentric Sky
Author-email: django@concentricsky.com
License: Apache2
Platform: UNKNOWN
